jupyter_vtk/__init__.py
jupyter_vtk/_frontend.py
jupyter_vtk/_version.py
jupyter_vtk/vtkwidget.py
jupyter_vtk/labextension/jupyter_vtk-0.3.0.tgz
jupyter_vtk/labextension/jupyter_vtk-0.3.1.tgz
jupyter_vtk/nbextension/__init__.py
jupyter_vtk/nbextension/static/index.js
jupyter_vtk/nbextension/static/index.js.map
jupyter_vtk/tests/__init__.py
jupyter_vtk/tests/conftest.py
jupyter_vtk/tests/test_example.py
jupyter_vtk/tests/test_nbextension_path.py
jupyter_vtk/tools/__init__.py
jupyter_vtk/tools/tools.py
jupyter_vtk-0.3.1.dev0.data/data/etc/jupyter/nbconfig/notebook.d/jupyter_vtk.json
jupyter_vtk-0.3.1.dev0.data/data/share/jupyter/lab/extensions/jupyter_vtk-0.3.1.tgz
jupyter_vtk-0.3.1.dev0.data/data/share/jupyter/nbextensions/jupyter_vtk/index.js
jupyter_vtk-0.3.1.dev0.data/data/share/jupyter/nbextensions/jupyter_vtk/index.js.map
jupyter_vtk-0.3.1.dev0.data/data/share/jupyter/nbextensions/jupyter_vtk/itk/PolyDataIOs/VTKXMLFileReader.js
jupyter_vtk-0.3.1.dev0.data/data/share/jupyter/nbextensions/jupyter_vtk/itk/PolyDataIOs/VTKXMLFileReaderWasm.js
jupyter_vtk-0.3.1.dev0.data/data/share/jupyter/nbextensions/jupyter_vtk/itk/PolyDataIOs/VTKXMLFileReaderWasm.wasm
jupyter_vtk-0.3.1.dev0.data/data/share/jupyter/nbextensions/jupyter_vtk/itk/WebWorkers/ImageIO.worker.js
jupyter_vtk-0.3.1.dev0.data/data/share/jupyter/nbextensions/jupyter_vtk/itk/WebWorkers/MeshIO.worker.js
jupyter_vtk-0.3.1.dev0.data/data/share/jupyter/nbextensions/jupyter_vtk/itk/WebWorkers/Pipeline.worker.js
jupyter_vtk-0.3.1.dev0.dist-info/LICENSE.txt
jupyter_vtk-0.3.1.dev0.dist-info/METADATA
jupyter_vtk-0.3.1.dev0.dist-info/WHEEL
jupyter_vtk-0.3.1.dev0.dist-info/top_level.txt
jupyter_vtk-0.3.1.dev0.dist-info/RECORD
